si/__init__.py
si/api.py
si/errors.py
sitm-0.1.dist-info/METADATA
sitm-0.1.dist-info/RECORD
sitm-0.1.dist-info/WHEEL
sitm-0.1.dist-info/top_level.txt
sitm-0.1.dist-info/zip-safe
